[{"pk": 8, "model": "dados.unidespas", "fields": {"unidespa": "cm", "descricao": "cent\u00edmetro"}}, {"pk": 2, "model": "dados.unidespas", "fields": {"unidespa": "km", "descricao": "quilometro"}}, {"pk": 5, "model": "dados.unidespas", "fields": {"unidespa": "km_h", "descricao": "quilometros por hora"}}, {"pk": 6, "model": "dados.unidespas", "fields": {"unidespa": "l", "descricao": "litro"}}, {"pk": 1, "model": "dados.unidespas", "fields": {"unidespa": "m", "descricao": "metro"}}, {"pk": 3, "model": "dados.unidespas", "fields": {"unidespa": "metro_quadrado", "descricao": "metro quadrado"}}, {"pk": 4, "model": "dados.unidespas", "fields": {"unidespa": "mm", "descricao": "milimetro"}}, {"pk": 7, "model": "dados.unidespas", "fields": {"unidespa": "vezes", "descricao": "vezes"}}]